[
    {
        "x1": 1586,
        "y1": 100,
        "x2": 1708,
        "y2": 241,
        "class_id": 0
    },
    {
        "x1": 1712,
        "y1": 106,
        "x2": 1840,
        "y2": 248,
        "class_id": 0
    },
    {
        "x1": 946,
        "y1": 69,
        "x2": 1065,
        "y2": 214,
        "class_id": 0
    },
    {
        "x1": 314,
        "y1": 38,
        "x2": 433,
        "y2": 184,
        "class_id": 0
    },
    {
        "x1": 692,
        "y1": 54,
        "x2": 815,
        "y2": 198,
        "class_id": 0
    },
    {
        "x1": 1071,
        "y1": 73,
        "x2": 1188,
        "y2": 215,
        "class_id": 0
    },
    {
        "x1": 187,
        "y1": 31,
        "x2": 303,
        "y2": 181,
        "class_id": 0
    },
    {
        "x1": 438,
        "y1": 35,
        "x2": 554,
        "y2": 179,
        "class_id": 0
    },
    {
        "x1": 561,
        "y1": 50,
        "x2": 683,
        "y2": 194,
        "class_id": 0
    },
    {
        "x1": 1974,
        "y1": 122,
        "x2": 2083,
        "y2": 256,
        "class_id": 0
    },
    {
        "x1": 1197,
        "y1": 82,
        "x2": 1320,
        "y2": 226,
        "class_id": 0
    },
    {
        "x1": 1849,
        "y1": 112,
        "x2": 1963,
        "y2": 252,
        "class_id": 0
    },
    {
        "x1": 1451,
        "y1": 90,
        "x2": 1578,
        "y2": 241,
        "class_id": 0
    },
    {
        "x1": 815,
        "y1": 60,
        "x2": 936,
        "y2": 211,
        "class_id": 0
    },
    {
        "x1": 50,
        "y1": 27,
        "x2": 165,
        "y2": 170,
        "class_id": 0
    },
    {
        "x1": 2114,
        "y1": 0,
        "x2": 2185,
        "y2": 55,
        "class_id": 0
    },
    {
        "x1": 1329,
        "y1": 180,
        "x2": 1381,
        "y2": 231,
        "class_id": 1
    },
    {
        "x1": 2105,
        "y1": 206,
        "x2": 2175,
        "y2": 269,
        "class_id": 1
    },
    {
        "x1": 0,
        "y1": 247,
        "x2": 39,
        "y2": 287,
        "class_id": 0
    }
]