[
    {
        "x1": 45,
        "y1": 27,
        "x2": 154,
        "y2": 163,
        "class_id": 0
    },
    {
        "x1": 165,
        "y1": 33,
        "x2": 273,
        "y2": 167,
        "class_id": 0
    },
    {
        "x1": 861,
        "y1": 62,
        "x2": 968,
        "y2": 195,
        "class_id": 0
    },
    {
        "x1": 975,
        "y1": 70,
        "x2": 1079,
        "y2": 192,
        "class_id": 0
    },
    {
        "x1": 401,
        "y1": 44,
        "x2": 504,
        "y2": 174,
        "class_id": 0
    },
    {
        "x1": 1206,
        "y1": 74,
        "x2": 1315,
        "y2": 202,
        "class_id": 0
    },
    {
        "x1": 282,
        "y1": 42,
        "x2": 384,
        "y2": 163,
        "class_id": 0
    },
    {
        "x1": 628,
        "y1": 55,
        "x2": 726,
        "y2": 185,
        "class_id": 0
    },
    {
        "x1": 1096,
        "y1": 73,
        "x2": 1196,
        "y2": 198,
        "class_id": 0
    },
    {
        "x1": 1324,
        "y1": 90,
        "x2": 1413,
        "y2": 205,
        "class_id": 0
    },
    {
        "x1": 741,
        "y1": 63,
        "x2": 849,
        "y2": 182,
        "class_id": 0
    },
    {
        "x1": 519,
        "y1": 45,
        "x2": 621,
        "y2": 205,
        "class_id": 0
    },
    {
        "x1": 1429,
        "y1": 159,
        "x2": 1480,
        "y2": 210,
        "class_id": 1
    }
]