[
    {
        "x1": 142,
        "y1": 5,
        "x2": 187,
        "y2": 58,
        "class_id": 0
    },
    {
        "x1": 689,
        "y1": 2,
        "x2": 733,
        "y2": 56,
        "class_id": 0
    },
    {
        "x1": 831,
        "y1": 3,
        "x2": 880,
        "y2": 57,
        "class_id": 0
    },
    {
        "x1": 194,
        "y1": 1,
        "x2": 239,
        "y2": 57,
        "class_id": 0
    },
    {
        "x1": 92,
        "y1": 6,
        "x2": 136,
        "y2": 56,
        "class_id": 0
    },
    {
        "x1": 0,
        "y1": 6,
        "x2": 39,
        "y2": 59,
        "class_id": 0
    },
    {
        "x1": 245,
        "y1": 4,
        "x2": 291,
        "y2": 55,
        "class_id": 0
    },
    {
        "x1": 737,
        "y1": 2,
        "x2": 783,
        "y2": 56,
        "class_id": 0
    },
    {
        "x1": 493,
        "y1": 3,
        "x2": 537,
        "y2": 57,
        "class_id": 0
    },
    {
        "x1": 1049,
        "y1": 0,
        "x2": 1097,
        "y2": 55,
        "class_id": 0
    },
    {
        "x1": 296,
        "y1": 2,
        "x2": 338,
        "y2": 56,
        "class_id": 0
    },
    {
        "x1": 591,
        "y1": 0,
        "x2": 638,
        "y2": 55,
        "class_id": 0
    },
    {
        "x1": 643,
        "y1": 0,
        "x2": 688,
        "y2": 57,
        "class_id": 0
    },
    {
        "x1": 998,
        "y1": 2,
        "x2": 1047,
        "y2": 56,
        "class_id": 0
    },
    {
        "x1": 441,
        "y1": 5,
        "x2": 485,
        "y2": 56,
        "class_id": 0
    },
    {
        "x1": 542,
        "y1": 3,
        "x2": 585,
        "y2": 55,
        "class_id": 0
    },
    {
        "x1": 42,
        "y1": 3,
        "x2": 88,
        "y2": 57,
        "class_id": 0
    },
    {
        "x1": 886,
        "y1": 1,
        "x2": 934,
        "y2": 58,
        "class_id": 0
    },
    {
        "x1": 393,
        "y1": 4,
        "x2": 440,
        "y2": 55,
        "class_id": 0
    },
    {
        "x1": 341,
        "y1": 1,
        "x2": 387,
        "y2": 56,
        "class_id": 0
    },
    {
        "x1": 1103,
        "y1": 1,
        "x2": 1149,
        "y2": 55,
        "class_id": 0
    },
    {
        "x1": 790,
        "y1": 1,
        "x2": 828,
        "y2": 53,
        "class_id": 0
    },
    {
        "x1": 1160,
        "y1": 0,
        "x2": 1208,
        "y2": 56,
        "class_id": 0
    },
    {
        "x1": 939,
        "y1": 0,
        "x2": 992,
        "y2": 58,
        "class_id": 0
    }
]