[
    {
        "x1": 2382,
        "y1": 9,
        "x2": 2504,
        "y2": 140,
        "class_id": 0
    },
    {
        "x1": 507,
        "y1": 8,
        "x2": 613,
        "y2": 139,
        "class_id": 0
    },
    {
        "x1": 0,
        "y1": 8,
        "x2": 91,
        "y2": 139,
        "class_id": 0
    },
    {
        "x1": 3090,
        "y1": 8,
        "x2": 3211,
        "y2": 140,
        "class_id": 0
    },
    {
        "x1": 3226,
        "y1": 5,
        "x2": 3351,
        "y2": 140,
        "class_id": 0
    },
    {
        "x1": 2111,
        "y1": 6,
        "x2": 2230,
        "y2": 138,
        "class_id": 0
    },
    {
        "x1": 108,
        "y1": 7,
        "x2": 219,
        "y2": 140,
        "class_id": 0
    },
    {
        "x1": 2671,
        "y1": 8,
        "x2": 2791,
        "y2": 139,
        "class_id": 0
    },
    {
        "x1": 913,
        "y1": 6,
        "x2": 1005,
        "y2": 131,
        "class_id": 0
    },
    {
        "x1": 771,
        "y1": 6,
        "x2": 893,
        "y2": 135,
        "class_id": 0
    },
    {
        "x1": 2526,
        "y1": 8,
        "x2": 2646,
        "y2": 136,
        "class_id": 0
    },
    {
        "x1": 1292,
        "y1": 5,
        "x2": 1396,
        "y2": 136,
        "class_id": 0
    },
    {
        "x1": 632,
        "y1": 6,
        "x2": 739,
        "y2": 136,
        "class_id": 0
    },
    {
        "x1": 240,
        "y1": 8,
        "x2": 351,
        "y2": 140,
        "class_id": 0
    },
    {
        "x1": 1152,
        "y1": 6,
        "x2": 1265,
        "y2": 138,
        "class_id": 0
    },
    {
        "x1": 1415,
        "y1": 5,
        "x2": 1529,
        "y2": 139,
        "class_id": 0
    },
    {
        "x1": 1692,
        "y1": 6,
        "x2": 1805,
        "y2": 136,
        "class_id": 0
    },
    {
        "x1": 1970,
        "y1": 6,
        "x2": 2086,
        "y2": 140,
        "class_id": 0
    },
    {
        "x1": 376,
        "y1": 10,
        "x2": 480,
        "y2": 140,
        "class_id": 0
    },
    {
        "x1": 1022,
        "y1": 9,
        "x2": 1132,
        "y2": 136,
        "class_id": 0
    },
    {
        "x1": 2250,
        "y1": 13,
        "x2": 2364,
        "y2": 140,
        "class_id": 0
    },
    {
        "x1": 1829,
        "y1": 12,
        "x2": 1927,
        "y2": 137,
        "class_id": 0
    },
    {
        "x1": 3373,
        "y1": 4,
        "x2": 3498,
        "y2": 136,
        "class_id": 0
    },
    {
        "x1": 2806,
        "y1": 10,
        "x2": 2914,
        "y2": 138,
        "class_id": 0
    },
    {
        "x1": 1550,
        "y1": 5,
        "x2": 1662,
        "y2": 135,
        "class_id": 0
    },
    {
        "x1": 2948,
        "y1": 18,
        "x2": 3062,
        "y2": 129,
        "class_id": 0
    }
]