[
    {
        "x1": 1154,
        "y1": 5,
        "x2": 1236,
        "y2": 99,
        "class_id": 0
    },
    {
        "x1": 887,
        "y1": 10,
        "x2": 966,
        "y2": 102,
        "class_id": 0
    },
    {
        "x1": 2141,
        "y1": 4,
        "x2": 2217,
        "y2": 97,
        "class_id": 0
    },
    {
        "x1": 451,
        "y1": 3,
        "x2": 529,
        "y2": 100,
        "class_id": 0
    },
    {
        "x1": 1601,
        "y1": 4,
        "x2": 1677,
        "y2": 98,
        "class_id": 0
    },
    {
        "x1": 711,
        "y1": 7,
        "x2": 788,
        "y2": 100,
        "class_id": 0
    },
    {
        "x1": 979,
        "y1": 7,
        "x2": 1052,
        "y2": 100,
        "class_id": 0
    },
    {
        "x1": 1419,
        "y1": 5,
        "x2": 1502,
        "y2": 101,
        "class_id": 0
    },
    {
        "x1": 1689,
        "y1": 5,
        "x2": 1765,
        "y2": 100,
        "class_id": 0
    },
    {
        "x1": 1,
        "y1": 8,
        "x2": 82,
        "y2": 97,
        "class_id": 0
    },
    {
        "x1": 1958,
        "y1": 5,
        "x2": 2039,
        "y2": 103,
        "class_id": 0
    },
    {
        "x1": 1865,
        "y1": 4,
        "x2": 1941,
        "y2": 98,
        "class_id": 0
    },
    {
        "x1": 625,
        "y1": 6,
        "x2": 699,
        "y2": 99,
        "class_id": 0
    },
    {
        "x1": 542,
        "y1": 6,
        "x2": 616,
        "y2": 99,
        "class_id": 0
    },
    {
        "x1": 97,
        "y1": 5,
        "x2": 177,
        "y2": 95,
        "class_id": 0
    },
    {
        "x1": 185,
        "y1": 4,
        "x2": 259,
        "y2": 97,
        "class_id": 0
    },
    {
        "x1": 360,
        "y1": 6,
        "x2": 442,
        "y2": 100,
        "class_id": 0
    },
    {
        "x1": 1778,
        "y1": 5,
        "x2": 1854,
        "y2": 99,
        "class_id": 0
    },
    {
        "x1": 2053,
        "y1": 7,
        "x2": 2126,
        "y2": 98,
        "class_id": 0
    },
    {
        "x1": 1246,
        "y1": 3,
        "x2": 1325,
        "y2": 99,
        "class_id": 0
    },
    {
        "x1": 275,
        "y1": 2,
        "x2": 344,
        "y2": 94,
        "class_id": 0
    },
    {
        "x1": 797,
        "y1": 10,
        "x2": 871,
        "y2": 99,
        "class_id": 0
    },
    {
        "x1": 1512,
        "y1": 5,
        "x2": 1588,
        "y2": 99,
        "class_id": 0
    },
    {
        "x1": 2231,
        "y1": 2,
        "x2": 2273,
        "y2": 97,
        "class_id": 0
    },
    {
        "x1": 1069,
        "y1": 20,
        "x2": 1142,
        "y2": 92,
        "class_id": 0
    },
    {
        "x1": 1329,
        "y1": 50,
        "x2": 1384,
        "y2": 103,
        "class_id": 1
    }
]