[
    {
        "x1": 767,
        "y1": 12,
        "x2": 828,
        "y2": 82,
        "class_id": 0
    },
    {
        "x1": 34,
        "y1": 9,
        "x2": 104,
        "y2": 92,
        "class_id": 0
    },
    {
        "x1": 968,
        "y1": 16,
        "x2": 1020,
        "y2": 80,
        "class_id": 0
    },
    {
        "x1": 1758,
        "y1": 13,
        "x2": 1820,
        "y2": 91,
        "class_id": 0
    },
    {
        "x1": 430,
        "y1": 8,
        "x2": 489,
        "y2": 77,
        "class_id": 0
    },
    {
        "x1": 119,
        "y1": 12,
        "x2": 180,
        "y2": 91,
        "class_id": 0
    },
    {
        "x1": 1168,
        "y1": 19,
        "x2": 1220,
        "y2": 86,
        "class_id": 0
    },
    {
        "x1": 563,
        "y1": 9,
        "x2": 620,
        "y2": 77,
        "class_id": 0
    },
    {
        "x1": 1496,
        "y1": 26,
        "x2": 1551,
        "y2": 93,
        "class_id": 0
    },
    {
        "x1": 631,
        "y1": 13,
        "x2": 689,
        "y2": 79,
        "class_id": 0
    },
    {
        "x1": 1099,
        "y1": 18,
        "x2": 1153,
        "y2": 86,
        "class_id": 0
    },
    {
        "x1": 701,
        "y1": 13,
        "x2": 754,
        "y2": 79,
        "class_id": 0
    },
    {
        "x1": 499,
        "y1": 13,
        "x2": 547,
        "y2": 76,
        "class_id": 0
    },
    {
        "x1": 835,
        "y1": 12,
        "x2": 891,
        "y2": 83,
        "class_id": 0
    },
    {
        "x1": 279,
        "y1": 18,
        "x2": 340,
        "y2": 90,
        "class_id": 0
    },
    {
        "x1": 1567,
        "y1": 31,
        "x2": 1618,
        "y2": 94,
        "class_id": 0
    },
    {
        "x1": 1036,
        "y1": 16,
        "x2": 1085,
        "y2": 84,
        "class_id": 0
    },
    {
        "x1": 204,
        "y1": 17,
        "x2": 264,
        "y2": 89,
        "class_id": 0
    },
    {
        "x1": 1302,
        "y1": 24,
        "x2": 1355,
        "y2": 85,
        "class_id": 0
    },
    {
        "x1": 1693,
        "y1": 34,
        "x2": 1746,
        "y2": 96,
        "class_id": 0
    },
    {
        "x1": 1628,
        "y1": 32,
        "x2": 1679,
        "y2": 95,
        "class_id": 0
    },
    {
        "x1": 1368,
        "y1": 25,
        "x2": 1417,
        "y2": 87,
        "class_id": 0
    },
    {
        "x1": 1436,
        "y1": 26,
        "x2": 1485,
        "y2": 92,
        "class_id": 0
    },
    {
        "x1": 353,
        "y1": 24,
        "x2": 409,
        "y2": 92,
        "class_id": 0
    },
    {
        "x1": 1845,
        "y1": 54,
        "x2": 1887,
        "y2": 93,
        "class_id": 1
    },
    {
        "x1": 898,
        "y1": 53,
        "x2": 926,
        "y2": 90,
        "class_id": 1
    },
    {
        "x1": 1231,
        "y1": 56,
        "x2": 1261,
        "y2": 89,
        "class_id": 1
    },
    {
        "x1": 895,
        "y1": 57,
        "x2": 928,
        "y2": 96,
        "class_id": 1
    }
]