[
    {
        "x1": 726,
        "y1": 6,
        "x2": 782,
        "y2": 81,
        "class_id": 0
    },
    {
        "x1": 884,
        "y1": 4,
        "x2": 948,
        "y2": 81,
        "class_id": 0
    },
    {
        "x1": 961,
        "y1": 1,
        "x2": 1022,
        "y2": 78,
        "class_id": 0
    },
    {
        "x1": 808,
        "y1": 3,
        "x2": 870,
        "y2": 78,
        "class_id": 0
    },
    {
        "x1": 109,
        "y1": 3,
        "x2": 166,
        "y2": 74,
        "class_id": 0
    },
    {
        "x1": 252,
        "y1": 9,
        "x2": 313,
        "y2": 83,
        "class_id": 0
    },
    {
        "x1": 1048,
        "y1": 8,
        "x2": 1102,
        "y2": 75,
        "class_id": 0
    },
    {
        "x1": 332,
        "y1": 13,
        "x2": 387,
        "y2": 82,
        "class_id": 0
    },
    {
        "x1": 652,
        "y1": 8,
        "x2": 702,
        "y2": 77,
        "class_id": 0
    },
    {
        "x1": 1288,
        "y1": 10,
        "x2": 1351,
        "y2": 74,
        "class_id": 0
    },
    {
        "x1": 1126,
        "y1": 7,
        "x2": 1191,
        "y2": 76,
        "class_id": 0
    },
    {
        "x1": 177,
        "y1": 10,
        "x2": 228,
        "y2": 81,
        "class_id": 0
    },
    {
        "x1": 417,
        "y1": 10,
        "x2": 474,
        "y2": 82,
        "class_id": 0
    },
    {
        "x1": 573,
        "y1": 8,
        "x2": 628,
        "y2": 79,
        "class_id": 0
    },
    {
        "x1": 39,
        "y1": 6,
        "x2": 93,
        "y2": 73,
        "class_id": 0
    },
    {
        "x1": 1205,
        "y1": 12,
        "x2": 1264,
        "y2": 76,
        "class_id": 0
    },
    {
        "x1": 503,
        "y1": 39,
        "x2": 545,
        "y2": 79,
        "class_id": 1
    },
    {
        "x1": 1373,
        "y1": 36,
        "x2": 1405,
        "y2": 70,
        "class_id": 1
    }
]