[
    {
        "x1": 1046,
        "y1": 3,
        "x2": 1103,
        "y2": 67,
        "class_id": 0
    },
    {
        "x1": 1247,
        "y1": 0,
        "x2": 1301,
        "y2": 66,
        "class_id": 0
    },
    {
        "x1": 842,
        "y1": 4,
        "x2": 901,
        "y2": 69,
        "class_id": 0
    },
    {
        "x1": 911,
        "y1": 5,
        "x2": 963,
        "y2": 68,
        "class_id": 0
    },
    {
        "x1": 1513,
        "y1": 3,
        "x2": 1569,
        "y2": 68,
        "class_id": 0
    },
    {
        "x1": 1380,
        "y1": 1,
        "x2": 1436,
        "y2": 66,
        "class_id": 0
    },
    {
        "x1": 68,
        "y1": 0,
        "x2": 123,
        "y2": 66,
        "class_id": 0
    },
    {
        "x1": 1715,
        "y1": 0,
        "x2": 1773,
        "y2": 68,
        "class_id": 0
    },
    {
        "x1": 649,
        "y1": 2,
        "x2": 703,
        "y2": 68,
        "class_id": 0
    },
    {
        "x1": 1579,
        "y1": 1,
        "x2": 1639,
        "y2": 67,
        "class_id": 0
    },
    {
        "x1": 1651,
        "y1": 1,
        "x2": 1705,
        "y2": 68,
        "class_id": 0
    },
    {
        "x1": 780,
        "y1": 3,
        "x2": 832,
        "y2": 67,
        "class_id": 0
    },
    {
        "x1": 1311,
        "y1": 0,
        "x2": 1367,
        "y2": 66,
        "class_id": 0
    },
    {
        "x1": 327,
        "y1": 0,
        "x2": 381,
        "y2": 64,
        "class_id": 0
    },
    {
        "x1": 580,
        "y1": 3,
        "x2": 637,
        "y2": 67,
        "class_id": 0
    },
    {
        "x1": 3,
        "y1": 3,
        "x2": 59,
        "y2": 69,
        "class_id": 0
    },
    {
        "x1": 1448,
        "y1": 2,
        "x2": 1503,
        "y2": 68,
        "class_id": 0
    },
    {
        "x1": 391,
        "y1": 6,
        "x2": 442,
        "y2": 67,
        "class_id": 0
    },
    {
        "x1": 133,
        "y1": 1,
        "x2": 187,
        "y2": 64,
        "class_id": 0
    },
    {
        "x1": 517,
        "y1": 4,
        "x2": 569,
        "y2": 65,
        "class_id": 0
    },
    {
        "x1": 1114,
        "y1": 5,
        "x2": 1168,
        "y2": 67,
        "class_id": 0
    },
    {
        "x1": 266,
        "y1": 1,
        "x2": 317,
        "y2": 64,
        "class_id": 0
    },
    {
        "x1": 716,
        "y1": 4,
        "x2": 770,
        "y2": 66,
        "class_id": 0
    },
    {
        "x1": 978,
        "y1": 2,
        "x2": 1035,
        "y2": 69,
        "class_id": 0
    },
    {
        "x1": 196,
        "y1": 2,
        "x2": 250,
        "y2": 66,
        "class_id": 0
    },
    {
        "x1": 455,
        "y1": 10,
        "x2": 506,
        "y2": 69,
        "class_id": 0
    },
    {
        "x1": 1786,
        "y1": 0,
        "x2": 1807,
        "y2": 69,
        "class_id": 0
    },
    {
        "x1": 1180,
        "y1": 33,
        "x2": 1211,
        "y2": 68,
        "class_id": 1
    }
]