[
    {
        "x1": 2407,
        "y1": 9,
        "x2": 2526,
        "y2": 146,
        "class_id": 0
    },
    {
        "x1": 1005,
        "y1": 17,
        "x2": 1124,
        "y2": 147,
        "class_id": 0
    },
    {
        "x1": 1410,
        "y1": 20,
        "x2": 1527,
        "y2": 148,
        "class_id": 0
    },
    {
        "x1": 2687,
        "y1": 10,
        "x2": 2807,
        "y2": 155,
        "class_id": 0
    },
    {
        "x1": 208,
        "y1": 14,
        "x2": 321,
        "y2": 146,
        "class_id": 0
    },
    {
        "x1": 2145,
        "y1": 13,
        "x2": 2251,
        "y2": 146,
        "class_id": 0
    },
    {
        "x1": 1139,
        "y1": 17,
        "x2": 1256,
        "y2": 145,
        "class_id": 0
    },
    {
        "x1": 2263,
        "y1": 6,
        "x2": 2384,
        "y2": 145,
        "class_id": 0
    },
    {
        "x1": 80,
        "y1": 12,
        "x2": 185,
        "y2": 148,
        "class_id": 0
    },
    {
        "x1": 342,
        "y1": 22,
        "x2": 456,
        "y2": 147,
        "class_id": 0
    },
    {
        "x1": 1546,
        "y1": 18,
        "x2": 1674,
        "y2": 153,
        "class_id": 0
    },
    {
        "x1": 1276,
        "y1": 23,
        "x2": 1390,
        "y2": 147,
        "class_id": 0
    },
    {
        "x1": 1844,
        "y1": 7,
        "x2": 1970,
        "y2": 145,
        "class_id": 0
    },
    {
        "x1": 478,
        "y1": 18,
        "x2": 583,
        "y2": 147,
        "class_id": 0
    },
    {
        "x1": 1993,
        "y1": 12,
        "x2": 2106,
        "y2": 148,
        "class_id": 0
    },
    {
        "x1": 889,
        "y1": 23,
        "x2": 989,
        "y2": 144,
        "class_id": 0
    },
    {
        "x1": 612,
        "y1": 27,
        "x2": 723,
        "y2": 146,
        "class_id": 0
    },
    {
        "x1": 2560,
        "y1": 41,
        "x2": 2665,
        "y2": 125,
        "class_id": 0
    },
    {
        "x1": 1710,
        "y1": 84,
        "x2": 1786,
        "y2": 155,
        "class_id": 1
    },
    {
        "x1": 767,
        "y1": 97,
        "x2": 845,
        "y2": 155,
        "class_id": 1
    },
    {
        "x1": 2853,
        "y1": 74,
        "x2": 2938,
        "y2": 150,
        "class_id": 1
    }
]