[
    {
        "x1": 307,
        "y1": 20,
        "x2": 380,
        "y2": 101,
        "class_id": 0
    },
    {
        "x1": 874,
        "y1": 25,
        "x2": 943,
        "y2": 109,
        "class_id": 0
    },
    {
        "x1": 27,
        "y1": 18,
        "x2": 97,
        "y2": 94,
        "class_id": 0
    },
    {
        "x1": 400,
        "y1": 21,
        "x2": 471,
        "y2": 101,
        "class_id": 0
    },
    {
        "x1": 124,
        "y1": 19,
        "x2": 194,
        "y2": 94,
        "class_id": 0
    },
    {
        "x1": 684,
        "y1": 25,
        "x2": 752,
        "y2": 105,
        "class_id": 0
    },
    {
        "x1": 215,
        "y1": 21,
        "x2": 284,
        "y2": 97,
        "class_id": 0
    },
    {
        "x1": 1250,
        "y1": 25,
        "x2": 1315,
        "y2": 106,
        "class_id": 0
    },
    {
        "x1": 589,
        "y1": 25,
        "x2": 662,
        "y2": 107,
        "class_id": 0
    },
    {
        "x1": 970,
        "y1": 23,
        "x2": 1037,
        "y2": 111,
        "class_id": 0
    },
    {
        "x1": 1157,
        "y1": 28,
        "x2": 1225,
        "y2": 106,
        "class_id": 0
    },
    {
        "x1": 1066,
        "y1": 26,
        "x2": 1135,
        "y2": 109,
        "class_id": 0
    },
    {
        "x1": 1344,
        "y1": 29,
        "x2": 1411,
        "y2": 110,
        "class_id": 0
    },
    {
        "x1": 778,
        "y1": 25,
        "x2": 847,
        "y2": 109,
        "class_id": 0
    },
    {
        "x1": 499,
        "y1": 26,
        "x2": 563,
        "y2": 102,
        "class_id": 0
    },
    {
        "x1": 1429,
        "y1": 72,
        "x2": 1458,
        "y2": 112,
        "class_id": 1
    }
]