[
    {
        "x1": 344,
        "y1": 9,
        "x2": 386,
        "y2": 54,
        "class_id": 0
    },
    {
        "x1": 1114,
        "y1": 4,
        "x2": 1162,
        "y2": 59,
        "class_id": 0
    },
    {
        "x1": 1051,
        "y1": 5,
        "x2": 1095,
        "y2": 58,
        "class_id": 0
    },
    {
        "x1": 876,
        "y1": 4,
        "x2": 926,
        "y2": 56,
        "class_id": 0
    },
    {
        "x1": 57,
        "y1": 4,
        "x2": 95,
        "y2": 51,
        "class_id": 0
    },
    {
        "x1": 105,
        "y1": 5,
        "x2": 142,
        "y2": 50,
        "class_id": 0
    },
    {
        "x1": 773,
        "y1": 18,
        "x2": 814,
        "y2": 68,
        "class_id": 0
    },
    {
        "x1": 251,
        "y1": 8,
        "x2": 289,
        "y2": 51,
        "class_id": 0
    },
    {
        "x1": 680,
        "y1": 15,
        "x2": 718,
        "y2": 60,
        "class_id": 0
    },
    {
        "x1": 11,
        "y1": 3,
        "x2": 48,
        "y2": 50,
        "class_id": 0
    },
    {
        "x1": 152,
        "y1": 5,
        "x2": 192,
        "y2": 51,
        "class_id": 0
    },
    {
        "x1": 295,
        "y1": 8,
        "x2": 336,
        "y2": 53,
        "class_id": 0
    },
    {
        "x1": 440,
        "y1": 8,
        "x2": 477,
        "y2": 55,
        "class_id": 0
    },
    {
        "x1": 392,
        "y1": 9,
        "x2": 432,
        "y2": 55,
        "class_id": 0
    },
    {
        "x1": 823,
        "y1": 20,
        "x2": 864,
        "y2": 69,
        "class_id": 0
    },
    {
        "x1": 726,
        "y1": 17,
        "x2": 765,
        "y2": 64,
        "class_id": 0
    },
    {
        "x1": 581,
        "y1": 13,
        "x2": 619,
        "y2": 59,
        "class_id": 0
    },
    {
        "x1": 536,
        "y1": 13,
        "x2": 571,
        "y2": 57,
        "class_id": 0
    },
    {
        "x1": 991,
        "y1": 5,
        "x2": 1036,
        "y2": 59,
        "class_id": 0
    },
    {
        "x1": 933,
        "y1": 6,
        "x2": 978,
        "y2": 59,
        "class_id": 0
    },
    {
        "x1": 631,
        "y1": 16,
        "x2": 668,
        "y2": 59,
        "class_id": 0
    },
    {
        "x1": 199,
        "y1": 6,
        "x2": 234,
        "y2": 50,
        "class_id": 0
    },
    {
        "x1": 1179,
        "y1": 27,
        "x2": 1215,
        "y2": 55,
        "class_id": 1
    },
    {
        "x1": 492,
        "y1": 27,
        "x2": 518,
        "y2": 54,
        "class_id": 1
    }
]